uncross/__about__.py
uncross/__init__.py
uncross/__main__.py
uncross/build_params.py
uncross/exceptions.py
uncross/invoke.py
uncross/logger.py
uncross/toolchains.py
uncross/cli/__init__.py
uncross/cli/uncross/__init__.py
uncross/cli/uncross/build.py
uncross/cli/uncross/check.py
uncross/cli/uncross/clean.py
uncross/cli/uncross/fmt.py
uncross/cli/uncross/group.py
uncross/cli/uncross/lint.py
uncross/cli/uncross/new.py
uncross/cli/uncross/release.py
uncross/cli/uncross/autocompletion/__init__.py
uncross/cli/uncross/autocompletion/bash.py
uncross/cli/uncross/autocompletion/fish.py
uncross/cli/uncross/autocompletion/group.py
uncross/cli/uncross/autocompletion/zsh.py
uncross/cli/uncross/config/__init__.py
uncross/cli/uncross/config/group.py
uncross/cli/uncross/config/list.py
uncross/cli/uncross/project/__init__.py
uncross/cli/uncross/project/group.py
uncross/cli/uncross/project/config/__init__.py
uncross/cli/uncross/project/config/group.py
uncross/cli/uncross/project/config/list.py
uncross/cli/uncross/toolchain/__init__.py
uncross/cli/uncross/toolchain/group.py
uncross/cli/uncross/toolchain/list.py
uncross/cli/uncross/toolchain/download/__init__.py
uncross/cli/uncross/toolchain/download/bootlin.py
uncross/cli/uncross/toolchain/download/group.py
uncross/cli/uncross/toolchain/register/__init__.py
uncross/cli/uncross/toolchain/register/bootlin.py
uncross/cli/uncross/toolchain/register/group.py
uncross/config/__init__.py
uncross/config/project/__init__.py
uncross/config/project/commit.py
uncross/config/project/parse.py
uncross/config/tool/__init__.py
uncross/config/tool/parse.py
uncross/git/__init__.py
uncross/git/repo.py
uncross/network/__init__.py
uncross/network/download.py
uncross/programs/__init__.py
uncross/programs/clang_format.py
uncross/programs/clang_tidy.py
uncross/programs/cmake.py
uncross/programs/code_checker.py
uncross/project/__init__.py
uncross/project/create.py
uncross/project/artifacts/__init__.py
uncross/project/artifacts/c_proj.py
uncross-0.1.1.dist-info/METADATA
uncross-0.1.1.dist-info/WHEEL
uncross-0.1.1.dist-info/entry_points.txt
uncross-0.1.1.dist-info/licenses/LICENSE.txt
uncross-0.1.1.dist-info/RECORD
