Metadata-Version: 2.3
Name: uncross
Version: 0.1.1
Summary: An opinionated meta build system for C cross-compilation.
Project-URL: Documentation, https://github.com/williamkborn/uncross#readme
Project-URL: Issues, https://github.com/williamkborn/uncross/issues
Project-URL: Source, https://github.com/williamkborn/uncross
Author-email: William Born <william.born.git@gmail.com>
License-Expression: MIT
License-File: LICENSE.txt
Classifier: Development Status :: 4 - Beta
Classifier: Programming Language :: Python
Classifier: Programming Language :: Python :: 3.8
Classifier: Programming Language :: Python :: 3.9
Classifier: Programming Language :: Python :: 3.10
Classifier: Programming Language :: Python :: 3.11
Classifier: Programming Language :: Python :: 3.12
Classifier: Programming Language :: Python :: Implementation :: CPython
Classifier: Programming Language :: Python :: Implementation :: PyPy
Requires-Python: >=3.8
Requires-Dist: auto-click-auto
Requires-Dist: click
Requires-Dist: codechecker
Requires-Dist: colorama
Requires-Dist: gitpython
Requires-Dist: prompt-toolkit
Requires-Dist: requests
Requires-Dist: rich
Requires-Dist: setuptools
Requires-Dist: toml
Provides-Extra: tools
Requires-Dist: clang-format; extra == 'tools'
Requires-Dist: clang-tidy; extra == 'tools'
Requires-Dist: cmake; extra == 'tools'
